{"facultyName":"AwP4.0s1_EEs1","events":[{"date":"2026-02-23","durationMin":90,"faculty":"AwP4.0s1 / EEs1","group":"W","instructor":"dr inż. S. Żaba","room":"A1","startTime":"09:15","status":"aktywne","subject":"Mikrokontrolery i sterowniki programowalne","type":"wykład"},{"date":"2026-02-23","durationMin":90,"faculty":"AwP4.0s1 / EEs1","group":"L1","instructor":"dr inż. S. Żaba","room":"06","startTime":"11:00","status":"aktywne","subject":"Mikrokontrolery i sterowniki programowalne","type":"laboratoria"},{"date":"2026-02-23","durationMin":135,"faculty":"AwP4.0s1 / EEs1","group":"Lk1","instructor":"dr inż. Z. Szular","room":"109B","startTime":"12:45","status":"aktywne","subject":"Energoelektronika przemysłowa","type":"laboratoria"},{"date":"2026-02-23","durationMin":90,"faculty":"AwP4.0s1 / EEs1","group":"W","instructor":"prof. K. Tomczyk","room":"A1","startTime":"16:15","status":"aktywne","subject":"Pomiary elektryczne wielkości nieelektrycznych","type":"wykład"},{"date":"2026-02-24","durationMin":135,"faculty":"AwP4.0s1 / EEs1","group":"L1","instructor":"dr inż. Z. Szular / mgr inż. M. Wawro","room":"013B","startTime":"09:30","status":"aktywne","subject":"Energoelektronika przemysłowa","type":"laboratoria"},{"date":"2026-02-24","durationMin":90,"faculty":"AwP4.0s1 / EEs1","group":"L3","instructor":"prof. K. Tomczyk","room":"208B","startTime":"10:15","status":"aktywne","subject":"Pomiary elektryczne wielkości nieelektrycznych","type":"laboratoria"},{"date":"2026-02-24","durationMin":90,"faculty":"AwP4.0s1 / EEs1","group":"L1","instructor":"prof. K. Tomczyk / dr inż. M. Sieja","room":"208B","startTime":"12:00","status":"aktywne","subject":"Pomiary elektryczne wielkości nieelektrycznych","type":"laboratoria"},{"date":"2026-02-24","durationMin":135,"faculty":"AwP4.0s1 / EEs1","group":"L3","instructor":"dr inż. Z. Szular / mgr inż. M. Wawro","room":"013B","startTime":"12:00","status":"aktywne","subject":"Energoelektronika przemysłowa","type":"laboratoria"},{"date":"2026-02-24","durationMin":90,"faculty":"AwP4.0s1 / EEs1","group":"W","instructor":"dr inż. M. Pawlik","room":"9","startTime":"14:30","status":"aktywne","subject":"Inżynieria sterowania","type":"wykład"},{"date":"2026-02-24","durationMin":90,"faculty":"AwP4.0s1 / EEs1","group":"Lk1","instructor":"dr inż. M. Pawlik","room":"18","startTime":"16:15","status":"aktywne","subject":"Inżynieria sterowania","type":"laboratoria"},{"date":"2026-02-24","durationMin":90,"faculty":"AwP4.0s1 / EEs1","group":"Lk2","instructor":"dr inż. M. Pawlik","room":"18","startTime":"18:00","status":"aktywne","subject":"Inżynieria sterowania","type":"laboratoria"},{"date":"2026-02-24","durationMin":90,"faculty":"AwP4.0s1 / EEs1","group":"P2","instructor":"dr inż. S. Żaba","room":"06","startTime":"19:45","status":"aktywne","subject":"Mikrokontrolery i sterowniki programowalne","type":"laboratoria"},{"date":"2026-02-26","durationMin":90,"faculty":"AwP4.0s1 / EEs1","group":"W","instructor":"prof. W. Mazgaj / dr inż. Z. Szular","room":"A4","startTime":"14:30","status":"aktywne","subject":"Energoelektronika przemysłowa","type":"wykład"},{"date":"2026-03-02","durationMin":90,"faculty":"AwP4.0s1 / EEs1","group":"W","instructor":"dr inż. S. Żaba","room":"A1","startTime":"09:15","status":"aktywne","subject":"Mikrokontrolery i sterowniki programowalne","type":"wykład"},{"date":"2026-03-02","durationMin":90,"faculty":"AwP4.0s1 / EEs1","group":"L2","instructor":"dr inż. S. Żaba","room":"06","startTime":"11:00","status":"aktywne","subject":"Mikrokontrolery i sterowniki programowalne","type":"laboratoria"},{"date":"2026-03-02","durationMin":135,"faculty":"AwP4.0s1 / EEs1","group":"Lk2","instructor":"dr inż. Z. Szular","room":"109B","startTime":"12:45","status":"aktywne","subject":"Energoelektronika przemysłowa","type":"laboratoria"},{"date":"2026-03-02","durationMin":90,"faculty":"AwP4.0s1 / EEs1","group":"W","instructor":"dr inż. A. Drwal","room":"A1","startTime":"16:15","status":"aktywne","subject":"Mikrokontrolery i sterowniki programowalne","type":"wykład"},{"date":"2026-03-02","durationMin":90,"faculty":"AwP4.0s1 / EEs1","group":"L3","instructor":"dr inż. A. Drwal","room":"06","startTime":"18:00","status":"aktywne","subject":"Mikrokontrolery i sterowniki programowalne","type":"laboratoria"},{"date":"2026-03-03","durationMin":135,"faculty":"AwP4.0s1 / EEs1","group":"L2","instructor":"dr inż. Z. Szular / mgr inż. M. Wawro","room":"013B","startTime":"09:30","status":"aktywne","subject":"Energoelektronika przemysłowa","type":"laboratoria"},{"date":"2026-03-03","durationMin":90,"faculty":"AwP4.0s1 / EEs1","group":"L2","instructor":"dr inż. M. Sieja","room":"208C","startTime":"12:00","status":"aktywne","subject":"Pomiary elektryczne wielkości nieelektrycznych","type":"laboratoria"},{"date":"2026-03-03","durationMin":90,"faculty":"AwP4.0s1 / EEs1","group":"P1","instructor":"dr inż. M. Pawlik","room":"18","startTime":"16:15","status":"aktywne","subject":"Inżynieria sterowania","type":"laboratoria"},{"date":"2026-03-03","durationMin":90,"faculty":"AwP4.0s1 / EEs1","group":"P2","instructor":"dr inż. M. Pawlik","room":"18","startTime":"18:00","status":"aktywne","subject":"Inżynieria sterowania","type":"laboratoria"},{"date":"2026-03-04","durationMin":90,"faculty":"AwP4.0s1 / EEs1","group":"W / C / S","instructor":"mgr T. Kuta","room":"9","startTime":"10:00","status":"aktywne","subject":"Techniki negocjacyjne","type":"wykład"},{"date":"2026-03-05","durationMin":90,"faculty":"AwP4.0s1 / EEs1","group":"W","instructor":"prof. W. Mazgaj / dr inż. Z. Szular","room":"A4","startTime":"14:30","status":"aktywne","subject":"Energoelektronika przemysłowa","type":"wykład"},{"date":"2026-03-09","durationMin":90,"faculty":"AwP4.0s1 / EEs1","group":"W","instructor":"dr inż. S. Żaba","room":"A1","startTime":"09:15","status":"aktywne","subject":"Mikrokontrolery i sterowniki programowalne","type":"wykład"},{"date":"2026-03-09","durationMin":90,"faculty":"AwP4.0s1 / EEs1","group":"L1","instructor":"dr inż. S. Żaba","room":"06","startTime":"11:00","status":"aktywne","subject":"Mikrokontrolery i sterowniki programowalne","type":"laboratoria"},{"date":"2026-03-09","durationMin":135,"faculty":"AwP4.0s1 / EEs1","group":"Lk1","instructor":"dr inż. Z. Szular","room":"109B","startTime":"12:45","status":"aktywne","subject":"Energoelektronika przemysłowa","type":"laboratoria"},{"date":"2026-03-09","durationMin":90,"faculty":"AwP4.0s1 / EEs1","group":"W","instructor":"prof. K. Tomczyk","room":"A1","startTime":"16:15","status":"aktywne","subject":"Pomiary elektryczne wielkości nieelektrycznych","type":"wykład"},{"date":"2026-03-10","durationMin":135,"faculty":"AwP4.0s1 / EEs1","group":"L1","instructor":"dr inż. Z. Szular / mgr inż. M. Wawro","room":"013B","startTime":"09:30","status":"aktywne","subject":"Energoelektronika przemysłowa","type":"laboratoria"},{"date":"2026-03-10","durationMin":90,"faculty":"AwP4.0s1 / EEs1","group":"L3","instructor":"prof. K. Tomczyk","room":"208B","startTime":"10:15","status":"aktywne","subject":"Pomiary elektryczne wielkości nieelektrycznych","type":"laboratoria"},{"date":"2026-03-10","durationMin":90,"faculty":"AwP4.0s1 / EEs1","group":"L1","instructor":"prof. K. Tomczyk / dr inż. M. Sieja","room":"208B","startTime":"12:00","status":"aktywne","subject":"Pomiary elektryczne wielkości nieelektrycznych","type":"laboratoria"},{"date":"2026-03-10","durationMin":135,"faculty":"AwP4.0s1 / EEs1","group":"L3","instructor":"dr inż. Z. Szular / mgr inż. M. Wawro","room":"013B","startTime":"12:00","status":"aktywne","subject":"Energoelektronika przemysłowa","type":"laboratoria"},{"date":"2026-03-10","durationMin":90,"faculty":"AwP4.0s1 / EEs1","group":"W","instructor":"dr inż. M. Pawlik","room":"9","startTime":"14:30","status":"aktywne","subject":"Inżynieria sterowania","type":"wykład"},{"date":"2026-03-10","durationMin":90,"faculty":"AwP4.0s1 / EEs1","group":"Lk1","instructor":"dr inż. M. Pawlik","room":"18","startTime":"16:15","status":"aktywne","subject":"Inżynieria sterowania","type":"laboratoria"},{"date":"2026-03-10","durationMin":90,"faculty":"AwP4.0s1 / EEs1","group":"Lk2","instructor":"dr inż. M. Pawlik","room":"18","startTime":"18:00","status":"aktywne","subject":"Inżynieria sterowania","type":"laboratoria"},{"date":"2026-03-10","durationMin":90,"faculty":"AwP4.0s1 / EEs1","group":"P2","instructor":"dr inż. S. Żaba","room":"06","startTime":"19:45","status":"aktywne","subject":"Mikrokontrolery i sterowniki programowalne","type":"laboratoria"},{"date":"2026-03-11","durationMin":90,"faculty":"AwP4.0s1 / EEs1","group":"W / C / S","instructor":"mgr T. Kuta","room":"9","startTime":"10:00","status":"aktywne","subject":"Techniki negocjacyjne","type":"wykład"},{"date":"2026-03-12","durationMin":90,"faculty":"AwP4.0s1 / EEs1","group":"W","instructor":"prof. W. Mazgaj / dr inż. Z. Szular","room":"A4","startTime":"14:30","status":"aktywne","subject":"Energoelektronika przemysłowa","type":"wykład"},{"date":"2026-03-16","durationMin":90,"faculty":"AwP4.0s1 / EEs1","group":"W","instructor":"dr inż. S. Żaba","room":"A1","startTime":"09:15","status":"aktywne","subject":"Mikrokontrolery i sterowniki programowalne","type":"wykład"},{"date":"2026-03-16","durationMin":90,"faculty":"AwP4.0s1 / EEs1","group":"L2","instructor":"dr inż. S. Żaba","room":"06","startTime":"11:00","status":"aktywne","subject":"Mikrokontrolery i sterowniki programowalne","type":"laboratoria"},{"date":"2026-03-16","durationMin":135,"faculty":"AwP4.0s1 / EEs1","group":"Lk2","instructor":"dr inż. Z. Szular","room":"109B","startTime":"12:45","status":"aktywne","subject":"Energoelektronika przemysłowa","type":"laboratoria"},{"date":"2026-03-16","durationMin":90,"faculty":"AwP4.0s1 / EEs1","group":"W","instructor":"dr inż. A. Drwal","room":"A1","startTime":"16:15","status":"aktywne","subject":"Mikrokontrolery i sterowniki programowalne","type":"wykład"},{"date":"2026-03-16","durationMin":90,"faculty":"AwP4.0s1 / EEs1","group":"L3","instructor":"dr inż. A. Drwal","room":"06","startTime":"18:00","status":"aktywne","subject":"Mikrokontrolery i sterowniki programowalne","type":"laboratoria"},{"date":"2026-03-17","durationMin":135,"faculty":"AwP4.0s1 / EEs1","group":"L2","instructor":"dr inż. Z. Szular / mgr inż. M. Wawro","room":"013B","startTime":"09:30","status":"aktywne","subject":"Energoelektronika przemysłowa","type":"laboratoria"},{"date":"2026-03-17","durationMin":90,"faculty":"AwP4.0s1 / EEs1","group":"L2","instructor":"dr inż. M. Sieja","room":"208C","startTime":"12:00","status":"aktywne","subject":"Pomiary elektryczne wielkości nieelektrycznych","type":"laboratoria"},{"date":"2026-03-17","durationMin":90,"faculty":"AwP4.0s1 / EEs1","group":"P1","instructor":"dr inż. M. Pawlik","room":"18","startTime":"16:15","status":"aktywne","subject":"Inżynieria sterowania","type":"laboratoria"},{"date":"2026-03-17","durationMin":90,"faculty":"AwP4.0s1 / EEs1","group":"P2","instructor":"dr inż. M. Pawlik","room":"18","startTime":"18:00","status":"aktywne","subject":"Inżynieria sterowania","type":"laboratoria"},{"date":"2026-03-18","durationMin":90,"faculty":"AwP4.0s1 / EEs1","group":"W / C / S","instructor":"mgr T. Kuta","room":"9","startTime":"10:00","status":"aktywne","subject":"Techniki negocjacyjne","type":"wykład"},{"date":"2026-03-19","durationMin":90,"faculty":"AwP4.0s1 / EEs1","group":"W","instructor":"prof. W. Mazgaj / dr inż. Z. Szular","room":"A4","startTime":"14:30","status":"aktywne","subject":"Energoelektronika przemysłowa","type":"wykład"},{"date":"2026-03-23","durationMin":90,"faculty":"AwP4.0s1 / EEs1","group":"P1","instructor":"dr inż. S. Żaba","room":"06","startTime":"09:15","status":"aktywne","subject":"Mikrokontrolery i sterowniki programowalne","type":"laboratoria"},{"date":"2026-03-23","durationMin":90,"faculty":"AwP4.0s1 / EEs1","group":"L1","instructor":"dr inż. S. Żaba","room":"06","startTime":"11:00","status":"aktywne","subject":"Mikrokontrolery i sterowniki programowalne","type":"laboratoria"},{"date":"2026-03-23","durationMin":135,"faculty":"AwP4.0s1 / EEs1","group":"Lk1","instructor":"dr inż. Z. Szular","room":"109B","startTime":"12:45","status":"aktywne","subject":"Energoelektronika przemysłowa","type":"laboratoria"},{"date":"2026-03-23","durationMin":90,"faculty":"AwP4.0s1 / EEs1","group":"W","instructor":"prof. K. Tomczyk","room":"A1","startTime":"16:15","status":"aktywne","subject":"Pomiary elektryczne wielkości nieelektrycznych","type":"wykład"},{"date":"2026-03-24","durationMin":135,"faculty":"AwP4.0s1 / EEs1","group":"L1","instructor":"dr inż. Z. Szular / mgr inż. M. Wawro","room":"013B","startTime":"09:30","status":"aktywne","subject":"Energoelektronika przemysłowa","type":"laboratoria"},{"date":"2026-03-24","durationMin":90,"faculty":"AwP4.0s1 / EEs1","group":"L3","instructor":"prof. K. Tomczyk","room":"208B","startTime":"10:15","status":"aktywne","subject":"Pomiary elektryczne wielkości nieelektrycznych","type":"laboratoria"},{"date":"2026-03-24","durationMin":90,"faculty":"AwP4.0s1 / EEs1","group":"L1","instructor":"prof. K. Tomczyk / dr inż. M. Sieja","room":"208B","startTime":"12:00","status":"aktywne","subject":"Pomiary elektryczne wielkości nieelektrycznych","type":"laboratoria"},{"date":"2026-03-24","durationMin":135,"faculty":"AwP4.0s1 / EEs1","group":"L3","instructor":"dr inż. Z. Szular / mgr inż. M. Wawro","room":"013B","startTime":"12:00","status":"aktywne","subject":"Energoelektronika przemysłowa","type":"laboratoria"},{"date":"2026-03-24","durationMin":90,"faculty":"AwP4.0s1 / EEs1","group":"W","instructor":"dr inż. M. Pawlik","room":"9","startTime":"14:30","status":"aktywne","subject":"Inżynieria sterowania","type":"wykład"},{"date":"2026-03-24","durationMin":90,"faculty":"AwP4.0s1 / EEs1","group":"Lk1","instructor":"dr inż. M. Pawlik","room":"18","startTime":"16:15","status":"aktywne","subject":"Inżynieria sterowania","type":"laboratoria"},{"date":"2026-03-24","durationMin":90,"faculty":"AwP4.0s1 / EEs1","group":"Lk2","instructor":"dr inż. M. Pawlik","room":"18","startTime":"18:00","status":"aktywne","subject":"Inżynieria sterowania","type":"laboratoria"},{"date":"2026-03-24","durationMin":90,"faculty":"AwP4.0s1 / EEs1","group":"P2","instructor":"dr inż. S. Żaba","room":"06","startTime":"19:45","status":"aktywne","subject":"Mikrokontrolery i sterowniki programowalne","type":"laboratoria"},{"date":"2026-03-25","durationMin":90,"faculty":"AwP4.0s1 / EEs1","group":"W / C / S","instructor":"mgr T. Kuta","room":"9","startTime":"10:00","status":"aktywne","subject":"Techniki negocjacyjne","type":"wykład"},{"date":"2026-03-26","durationMin":90,"faculty":"AwP4.0s1 / EEs1","group":"W","instructor":"prof. W. Mazgaj / dr inż. Z. Szular","room":"A4","startTime":"14:30","status":"aktywne","subject":"Energoelektronika przemysłowa","type":"wykład"},{"date":"2026-03-30","durationMin":90,"faculty":"AwP4.0s1 / EEs1","group":"P1","instructor":"dr inż. S. Żaba","room":"06","startTime":"09:15","status":"aktywne","subject":"Mikrokontrolery i sterowniki programowalne","type":"laboratoria"},{"date":"2026-03-30","durationMin":90,"faculty":"AwP4.0s1 / EEs1","group":"L2","instructor":"dr inż. S. Żaba","room":"06","startTime":"11:00","status":"aktywne","subject":"Mikrokontrolery i sterowniki programowalne","type":"laboratoria"},{"date":"2026-03-30","durationMin":135,"faculty":"AwP4.0s1 / EEs1","group":"Lk2","instructor":"dr inż. Z. Szular","room":"109B","startTime":"12:45","status":"aktywne","subject":"Energoelektronika przemysłowa","type":"laboratoria"},{"date":"2026-03-30","durationMin":90,"faculty":"AwP4.0s1 / EEs1","group":"W","instructor":"dr inż. A. Drwal","room":"A1","startTime":"16:15","status":"aktywne","subject":"Mikrokontrolery i sterowniki programowalne","type":"wykład"},{"date":"2026-03-30","durationMin":90,"faculty":"AwP4.0s1 / EEs1","group":"L3","instructor":"dr inż. A. Drwal","room":"06","startTime":"18:00","status":"aktywne","subject":"Mikrokontrolery i sterowniki programowalne","type":"laboratoria"},{"date":"2026-03-31","durationMin":135,"faculty":"AwP4.0s1 / EEs1","group":"L2","instructor":"dr inż. Z. Szular / mgr inż. M. Wawro","room":"013B","startTime":"09:30","status":"aktywne","subject":"Energoelektronika przemysłowa","type":"laboratoria"},{"date":"2026-03-31","durationMin":90,"faculty":"AwP4.0s1 / EEs1","group":"L2","instructor":"dr inż. M. Sieja","room":"208C","startTime":"12:00","status":"aktywne","subject":"Pomiary elektryczne wielkości nieelektrycznych","type":"laboratoria"},{"date":"2026-03-31","durationMin":90,"faculty":"AwP4.0s1 / EEs1","group":"P1","instructor":"dr inż. M. Pawlik","room":"18","startTime":"16:15","status":"aktywne","subject":"Inżynieria sterowania","type":"laboratoria"},{"date":"2026-03-31","durationMin":90,"faculty":"AwP4.0s1 / EEs1","group":"P2","instructor":"dr inż. M. Pawlik","room":"18","startTime":"18:00","status":"aktywne","subject":"Inżynieria sterowania","type":"laboratoria"},{"date":"2026-04-01","durationMin":900,"faculty":"AwP4.0s1 / EEs1","group":"Wszystkie grupy","instructor":"Brak","room":"-","startTime":"07:00","status":"wolne","subject":"Przerwa świąteczna","type":"święto"},{"date":"2026-04-02","durationMin":900,"faculty":"AwP4.0s1 / EEs1","group":"Wszystkie grupy","instructor":"Brak","room":"-","startTime":"07:00","status":"wolne","subject":"Przerwa świąteczna","type":"święto"},{"date":"2026-04-03","durationMin":900,"faculty":"AwP4.0s1 / EEs1","group":"Wszystkie grupy","instructor":"Brak","room":"-","startTime":"07:00","status":"wolne","subject":"Przerwa świąteczna","type":"święto"},{"date":"2026-04-04","durationMin":900,"faculty":"AwP4.0s1 / EEs1","group":"Wszystkie grupy","instructor":"Brak","room":"-","startTime":"07:00","status":"wolne","subject":"Przerwa świąteczna","type":"święto"},{"date":"2026-04-05","durationMin":900,"faculty":"AwP4.0s1 / EEs1","group":"Wszystkie grupy","instructor":"Brak","room":"-","startTime":"07:00","status":"wolne","subject":"Przerwa świąteczna","type":"święto"},{"date":"2026-04-06","durationMin":900,"faculty":"AwP4.0s1 / EEs1","group":"Wszystkie grupy","instructor":"Brak","room":"-","startTime":"07:00","status":"wolne","subject":"Przerwa świąteczna","type":"święto"},{"date":"2026-04-07","durationMin":900,"faculty":"AwP4.0s1 / EEs1","group":"Wszystkie grupy","instructor":"Brak","room":"-","startTime":"07:00","status":"wolne","subject":"Przerwa świąteczna","type":"święto"},{"date":"2026-04-08","durationMin":90,"faculty":"AwP4.0s1 / EEs1","group":"W / C / S","instructor":"mgr T. Kuta","room":"9","startTime":"10:00","status":"aktywne","subject":"Techniki negocjacyjne","type":"wykład"},{"date":"2026-04-09","durationMin":90,"faculty":"AwP4.0s1 / EEs1","group":"W","instructor":"prof. W. Mazgaj / dr inż. Z. Szular","room":"A4","startTime":"14:30","status":"aktywne","subject":"Energoelektronika przemysłowa","type":"wykład"},{"date":"2026-04-13","durationMin":90,"faculty":"AwP4.0s1 / EEs1","group":"P1","instructor":"dr inż. S. Żaba","room":"06","startTime":"09:15","status":"aktywne","subject":"Mikrokontrolery i sterowniki programowalne","type":"laboratoria"},{"date":"2026-04-13","durationMin":90,"faculty":"AwP4.0s1 / EEs1","group":"L2","instructor":"dr inż. S. Żaba","room":"06","startTime":"11:00","status":"aktywne","subject":"Mikrokontrolery i sterowniki programowalne","type":"laboratoria"},{"date":"2026-04-13","durationMin":135,"faculty":"AwP4.0s1 / EEs1","group":"Lk2","instructor":"dr inż. Z. Szular","room":"109B","startTime":"12:45","status":"aktywne","subject":"Energoelektronika przemysłowa","type":"laboratoria"},{"date":"2026-04-13","durationMin":45,"faculty":"AwP4.0s1 / EEs1","group":"W","instructor":"dr inż. A. Drwal","room":"A1","startTime":"16:15","status":"aktywne","subject":"Mikrokontrolery i sterowniki programowalne","type":"wykład"},{"date":"2026-04-13","durationMin":90,"faculty":"AwP4.0s1 / EEs1","group":"L3","instructor":"dr inż. A. Drwal","room":"06","startTime":"18:00","status":"aktywne","subject":"Mikrokontrolery i sterowniki programowalne","type":"laboratoria"},{"date":"2026-04-14","durationMin":135,"faculty":"AwP4.0s1 / EEs1","group":"L2","instructor":"dr inż. Z. Szular / mgr inż. M. Wawro","room":"013B","startTime":"09:30","status":"aktywne","subject":"Energoelektronika przemysłowa","type":"laboratoria"},{"date":"2026-04-14","durationMin":90,"faculty":"AwP4.0s1 / EEs1","group":"L2","instructor":"dr inż. M. Sieja","room":"208C","startTime":"12:00","status":"aktywne","subject":"Pomiary elektryczne wielkości nieelektrycznych","type":"laboratoria"},{"date":"2026-04-14","durationMin":90,"faculty":"AwP4.0s1 / EEs1","group":"P1","instructor":"dr inż. M. Pawlik","room":"18","startTime":"16:15","status":"aktywne","subject":"Inżynieria sterowania","type":"laboratoria"},{"date":"2026-04-14","durationMin":90,"faculty":"AwP4.0s1 / EEs1","group":"P2","instructor":"dr inż. M. Pawlik","room":"18","startTime":"18:00","status":"aktywne","subject":"Inżynieria sterowania","type":"laboratoria"},{"date":"2026-04-15","durationMin":90,"faculty":"AwP4.0s1 / EEs1","group":"W / C / S","instructor":"mgr T. Kuta","room":"9","startTime":"10:00","status":"aktywne","subject":"Techniki negocjacyjne","type":"wykład"},{"date":"2026-04-16","durationMin":90,"faculty":"AwP4.0s1 / EEs1","group":"W","instructor":"prof. W. Mazgaj / dr inż. Z. Szular","room":"A4","startTime":"14:30","status":"aktywne","subject":"Energoelektronika przemysłowa","type":"wykład"},{"date":"2026-04-20","durationMin":90,"faculty":"AwP4.0s1 / EEs1","group":"P1","instructor":"dr inż. S. Żaba","room":"06","startTime":"09:15","status":"aktywne","subject":"Mikrokontrolery i sterowniki programowalne","type":"laboratoria"},{"date":"2026-04-20","durationMin":90,"faculty":"AwP4.0s1 / EEs1","group":"L1","instructor":"dr inż. S. Żaba","room":"06","startTime":"11:00","status":"aktywne","subject":"Mikrokontrolery i sterowniki programowalne","type":"laboratoria"},{"date":"2026-04-20","durationMin":135,"faculty":"AwP4.0s1 / EEs1","group":"Lk1","instructor":"dr inż. Z. Szular","room":"109B","startTime":"12:45","status":"aktywne","subject":"Energoelektronika przemysłowa","type":"laboratoria"},{"date":"2026-04-20","durationMin":90,"faculty":"AwP4.0s1 / EEs1","group":"W","instructor":"prof. K. Tomczyk","room":"A1","startTime":"16:15","status":"aktywne","subject":"Pomiary elektryczne wielkości nieelektrycznych","type":"wykład"},{"date":"2026-04-21","durationMin":135,"faculty":"AwP4.0s1 / EEs1","group":"L1","instructor":"dr inż. Z. Szular / mgr inż. M. Wawro","room":"013B","startTime":"09:30","status":"aktywne","subject":"Energoelektronika przemysłowa","type":"laboratoria"},{"date":"2026-04-21","durationMin":90,"faculty":"AwP4.0s1 / EEs1","group":"L3","instructor":"prof. K. Tomczyk","room":"208B","startTime":"10:15","status":"aktywne","subject":"Pomiary elektryczne wielkości nieelektrycznych","type":"laboratoria"},{"date":"2026-04-21","durationMin":90,"faculty":"AwP4.0s1 / EEs1","group":"L1","instructor":"prof. K. Tomczyk / dr inż. M. Sieja","room":"208B","startTime":"12:00","status":"aktywne","subject":"Pomiary elektryczne wielkości nieelektrycznych","type":"laboratoria"},{"date":"2026-04-21","durationMin":135,"faculty":"AwP4.0s1 / EEs1","group":"L3","instructor":"dr inż. Z. Szular / mgr inż. M. Wawro","room":"013B","startTime":"12:00","status":"aktywne","subject":"Energoelektronika przemysłowa","type":"laboratoria"},{"date":"2026-04-21","durationMin":90,"faculty":"AwP4.0s1 / EEs1","group":"W","instructor":"dr inż. M. Pawlik","room":"9","startTime":"14:30","status":"aktywne","subject":"Inżynieria sterowania","type":"wykład"},{"date":"2026-04-21","durationMin":90,"faculty":"AwP4.0s1 / EEs1","group":"Lk1","instructor":"dr inż. M. Pawlik","room":"18","startTime":"16:15","status":"aktywne","subject":"Inżynieria sterowania","type":"laboratoria"},{"date":"2026-04-21","durationMin":90,"faculty":"AwP4.0s1 / EEs1","group":"Lk2","instructor":"dr inż. M. Pawlik","room":"18","startTime":"18:00","status":"aktywne","subject":"Inżynieria sterowania","type":"laboratoria"},{"date":"2026-04-21","durationMin":90,"faculty":"AwP4.0s1 / EEs1","group":"P2","instructor":"dr inż. S. Żaba","room":"06","startTime":"19:45","status":"aktywne","subject":"Mikrokontrolery i sterowniki programowalne","type":"laboratoria"},{"date":"2026-04-22","durationMin":90,"faculty":"AwP4.0s1 / EEs1","group":"W / C / S","instructor":"mgr T. Kuta","room":"9","startTime":"10:00","status":"aktywne","subject":"Techniki negocjacyjne","type":"wykład"},{"date":"2026-04-27","durationMin":90,"faculty":"AwP4.0s1 / EEs1","group":"P1","instructor":"dr inż. S. Żaba","room":"06","startTime":"09:15","status":"aktywne","subject":"Mikrokontrolery i sterowniki programowalne","type":"laboratoria"},{"date":"2026-04-27","durationMin":90,"faculty":"AwP4.0s1 / EEs1","group":"L2","instructor":"dr inż. S. Żaba","room":"06","startTime":"11:00","status":"aktywne","subject":"Mikrokontrolery i sterowniki programowalne","type":"laboratoria"},{"date":"2026-04-27","durationMin":135,"faculty":"AwP4.0s1 / EEs1","group":"Lk2","instructor":"dr inż. Z. Szular","room":"109B","startTime":"12:45","status":"aktywne","subject":"Energoelektronika przemysłowa","type":"laboratoria"},{"date":"2026-04-27","durationMin":90,"faculty":"AwP4.0s1 / EEs1","group":"L3","instructor":"dr inż. A. Drwal","room":"06","startTime":"18:00","status":"aktywne","subject":"Mikrokontrolery i sterowniki programowalne","type":"laboratoria"},{"date":"2026-04-28","durationMin":135,"faculty":"AwP4.0s1 / EEs1","group":"L2","instructor":"dr inż. Z. Szular / mgr inż. M. Wawro","room":"013B","startTime":"09:30","status":"aktywne","subject":"Energoelektronika przemysłowa","type":"laboratoria"},{"date":"2026-04-28","durationMin":90,"faculty":"AwP4.0s1 / EEs1","group":"L2","instructor":"dr inż. M. Sieja","room":"208C","startTime":"12:00","status":"aktywne","subject":"Pomiary elektryczne wielkości nieelektrycznych","type":"laboratoria"},{"date":"2026-04-28","durationMin":90,"faculty":"AwP4.0s1 / EEs1","group":"P1","instructor":"dr inż. M. Pawlik","room":"18","startTime":"16:15","status":"aktywne","subject":"Inżynieria sterowania","type":"laboratoria"},{"date":"2026-04-28","durationMin":90,"faculty":"AwP4.0s1 / EEs1","group":"P2","instructor":"dr inż. M. Pawlik","room":"18","startTime":"18:00","status":"aktywne","subject":"Inżynieria sterowania","type":"laboratoria"},{"date":"2026-04-29","durationMin":90,"faculty":"AwP4.0s1 / EEs1","group":"W / C / S","instructor":"mgr T. Kuta","room":"9","startTime":"10:00","status":"aktywne","subject":"Techniki negocjacyjne","type":"wykład"},{"date":"2026-05-01","durationMin":900,"faculty":"AwP4.0s1 / EEs1","group":"Wszystkie grupy","instructor":"Brak","room":"-","startTime":"07:00","status":"wolne","subject":"Majówka","type":"święto"},{"date":"2026-05-02","durationMin":900,"faculty":"AwP4.0s1 / EEs1","group":"Wszystkie grupy","instructor":"Brak","room":"-","startTime":"07:00","status":"wolne","subject":"Majówka","type":"święto"},{"date":"2026-05-03","durationMin":900,"faculty":"AwP4.0s1 / EEs1","group":"Wszystkie grupy","instructor":"Brak","room":"-","startTime":"07:00","status":"wolne","subject":"Majówka","type":"święto"},{"date":"2026-05-04","durationMin":900,"faculty":"AwP4.0s1 / EEs1","group":"Wszystkie grupy","instructor":"Brak","room":"-","startTime":"07:00","status":"wolne","subject":"Majówka","type":"święto"},{"date":"2026-05-05","durationMin":135,"faculty":"AwP4.0s1 / EEs1","group":"L1","instructor":"dr inż. Z. Szular / mgr inż. M. Wawro","room":"013B","startTime":"09:30","status":"aktywne","subject":"Energoelektronika przemysłowa","type":"laboratoria"},{"date":"2026-05-05","durationMin":90,"faculty":"AwP4.0s1 / EEs1","group":"L3","instructor":"prof. K. Tomczyk","room":"208B","startTime":"10:15","status":"aktywne","subject":"Pomiary elektryczne wielkości nieelektrycznych","type":"laboratoria"},{"date":"2026-05-05","durationMin":90,"faculty":"AwP4.0s1 / EEs1","group":"L1","instructor":"prof. K. Tomczyk / dr inż. M. Sieja","room":"208B","startTime":"12:00","status":"aktywne","subject":"Pomiary elektryczne wielkości nieelektrycznych","type":"laboratoria"},{"date":"2026-05-05","durationMin":135,"faculty":"AwP4.0s1 / EEs1","group":"L3","instructor":"dr inż. Z. Szular / mgr inż. M. Wawro","room":"013B","startTime":"12:00","status":"aktywne","subject":"Energoelektronika przemysłowa","type":"laboratoria"},{"date":"2026-05-05","durationMin":90,"faculty":"AwP4.0s1 / EEs1","group":"W","instructor":"dr inż. M. Pawlik","room":"9","startTime":"14:30","status":"aktywne","subject":"Inżynieria sterowania","type":"wykład"},{"date":"2026-05-05","durationMin":90,"faculty":"AwP4.0s1 / EEs1","group":"Lk1","instructor":"dr inż. M. Pawlik","room":"18","startTime":"16:15","status":"aktywne","subject":"Inżynieria sterowania","type":"laboratoria"},{"date":"2026-05-05","durationMin":90,"faculty":"AwP4.0s1 / EEs1","group":"Lk2","instructor":"dr inż. M. Pawlik","room":"18","startTime":"18:00","status":"aktywne","subject":"Inżynieria sterowania","type":"laboratoria"},{"date":"2026-05-05","durationMin":90,"faculty":"AwP4.0s1 / EEs1","group":"P2","instructor":"dr inż. S. Żaba","room":"06","startTime":"19:45","status":"aktywne","subject":"Mikrokontrolery i sterowniki programowalne","type":"laboratoria"},{"date":"2026-05-06","durationMin":90,"faculty":"AwP4.0s1 / EEs1","group":"W / C / S","instructor":"mgr T. Kuta","room":"9","startTime":"10:00","status":"aktywne","subject":"Techniki negocjacyjne","type":"wykład"},{"date":"2026-05-11","durationMin":90,"faculty":"AwP4.0s1 / EEs1","group":"P1","instructor":"dr inż. S. Żaba","room":"06","startTime":"09:15","status":"aktywne","subject":"Mikrokontrolery i sterowniki programowalne","type":"laboratoria"},{"date":"2026-05-11","durationMin":90,"faculty":"AwP4.0s1 / EEs1","group":"L2","instructor":"dr inż. S. Żaba","room":"06","startTime":"11:00","status":"aktywne","subject":"Mikrokontrolery i sterowniki programowalne","type":"laboratoria"},{"date":"2026-05-11","durationMin":90,"faculty":"AwP4.0s1 / EEs1","group":"L3","instructor":"dr inż. A. Drwal","room":"06","startTime":"18:00","status":"aktywne","subject":"Mikrokontrolery i sterowniki programowalne","type":"laboratoria"},{"date":"2026-05-12","durationMin":900,"faculty":"AwP4.0s1 / EEs1","group":"Wszystkie grupy","instructor":"Brak","room":"-","startTime":"07:00","status":"wolne","subject":"Święto Szkoły","type":"święto"},{"date":"2026-05-13","durationMin":90,"faculty":"AwP4.0s1 / EEs1","group":"W / C / S","instructor":"mgr T. Kuta","room":"9","startTime":"10:00","status":"aktywne","subject":"Techniki negocjacyjne","type":"wykład"},{"date":"2026-05-18","durationMin":90,"faculty":"AwP4.0s1 / EEs1","group":"P1","instructor":"dr inż. S. Żaba","room":"06","startTime":"09:15","status":"aktywne","subject":"Mikrokontrolery i sterowniki programowalne","type":"laboratoria"},{"date":"2026-05-18","durationMin":90,"faculty":"AwP4.0s1 / EEs1","group":"L1","instructor":"dr inż. S. Żaba","room":"06","startTime":"11:00","status":"aktywne","subject":"Mikrokontrolery i sterowniki programowalne","type":"laboratoria"},{"date":"2026-05-18","durationMin":135,"faculty":"AwP4.0s1 / EEs1","group":"Lk1","instructor":"dr inż. Z. Szular","room":"109B","startTime":"12:45","status":"aktywne","subject":"Energoelektronika przemysłowa","type":"laboratoria"},{"date":"2026-05-18","durationMin":135,"faculty":"AwP4.0s1 / EEs1","group":"W","instructor":"prof. K. Tomczyk","room":"A1","startTime":"15:30","status":"aktywne","subject":"Pomiary elektryczne wielkości nieelektrycznych","type":"wykład"},{"date":"2026-05-19","durationMin":90,"faculty":"AwP4.0s1 / EEs1","group":"L3","instructor":"prof. K. Tomczyk","room":"208B","startTime":"10:15","status":"aktywne","subject":"Pomiary elektryczne wielkości nieelektrycznych","type":"laboratoria"},{"date":"2026-05-19","durationMin":90,"faculty":"AwP4.0s1 / EEs1","group":"L1","instructor":"prof. K. Tomczyk / dr inż. M. Sieja","room":"208B","startTime":"12:00","status":"aktywne","subject":"Pomiary elektryczne wielkości nieelektrycznych","type":"laboratoria"},{"date":"2026-05-19","durationMin":90,"faculty":"AwP4.0s1 / EEs1","group":"W","instructor":"dr inż. M. Pawlik","room":"9","startTime":"14:30","status":"aktywne","subject":"Inżynieria sterowania","type":"wykład"},{"date":"2026-05-19","durationMin":90,"faculty":"AwP4.0s1 / EEs1","group":"Lk1","instructor":"dr inż. M. Pawlik","room":"18","startTime":"16:15","status":"aktywne","subject":"Inżynieria sterowania","type":"laboratoria"},{"date":"2026-05-19","durationMin":90,"faculty":"AwP4.0s1 / EEs1","group":"Lk2","instructor":"dr inż. M. Pawlik","room":"18","startTime":"18:00","status":"aktywne","subject":"Inżynieria sterowania","type":"laboratoria"},{"date":"2026-05-19","durationMin":90,"faculty":"AwP4.0s1 / EEs1","group":"P2","instructor":"dr inż. S. Żaba","room":"06","startTime":"19:45","status":"aktywne","subject":"Mikrokontrolery i sterowniki programowalne","type":"laboratoria"},{"date":"2026-05-20","durationMin":90,"faculty":"AwP4.0s1 / EEs1","group":"W / C / S","instructor":"mgr T. Kuta","room":"9","startTime":"10:00","status":"aktywne","subject":"Techniki negocjacyjne","type":"wykład"},{"date":"2026-05-24","durationMin":900,"faculty":"AwP4.0s1 / EEs1","group":"Wszystkie grupy","instructor":"Brak","room":"-","startTime":"07:00","status":"wolne","subject":"Zielone Świątki","type":"święto"},{"date":"2026-05-25","durationMin":90,"faculty":"AwP4.0s1 / EEs1","group":"L2","instructor":"dr inż. S. Żaba","room":"06","startTime":"11:00","status":"aktywne","subject":"Mikrokontrolery i sterowniki programowalne","type":"laboratoria"},{"date":"2026-05-25","durationMin":90,"faculty":"AwP4.0s1 / EEs1","group":"L3","instructor":"dr inż. A. Drwal","room":"06","startTime":"18:00","status":"aktywne","subject":"Mikrokontrolery i sterowniki programowalne","type":"laboratoria"},{"date":"2026-05-26","durationMin":90,"faculty":"AwP4.0s1 / EEs1","group":"L2","instructor":"dr inż. M. Sieja","room":"208C","startTime":"12:00","status":"aktywne","subject":"Pomiary elektryczne wielkości nieelektrycznych","type":"laboratoria"},{"date":"2026-05-26","durationMin":90,"faculty":"AwP4.0s1 / EEs1","group":"P1","instructor":"dr inż. M. Pawlik","room":"18","startTime":"16:15","status":"aktywne","subject":"Inżynieria sterowania","type":"laboratoria"},{"date":"2026-05-26","durationMin":90,"faculty":"AwP4.0s1 / EEs1","group":"P2","instructor":"dr inż. M. Pawlik","room":"18","startTime":"18:00","status":"aktywne","subject":"Inżynieria sterowania","type":"laboratoria"},{"date":"2026-05-27","durationMin":90,"faculty":"AwP4.0s1 / EEs1","group":"W / C / S","instructor":"mgr T. Kuta","room":"9","startTime":"10:00","status":"aktywne","subject":"Techniki negocjacyjne","type":"wykład"},{"date":"2026-06-01","durationMin":90,"faculty":"AwP4.0s1 / EEs1","group":"L1","instructor":"dr inż. S. Żaba","room":"06","startTime":"11:00","status":"aktywne","subject":"Mikrokontrolery i sterowniki programowalne","type":"laboratoria"},{"date":"2026-06-01","durationMin":90,"faculty":"AwP4.0s1 / EEs1","group":"W","instructor":"prof. K. Tomczyk","room":"A1","startTime":"16:15","status":"aktywne","subject":"Pomiary elektryczne wielkości nieelektrycznych","type":"wykład"},{"date":"2026-06-02","durationMin":90,"faculty":"AwP4.0s1 / EEs1","group":"L3","instructor":"prof. K. Tomczyk","room":"208B","startTime":"10:15","status":"aktywne","subject":"Pomiary elektryczne wielkości nieelektrycznych","type":"laboratoria"},{"date":"2026-06-02","durationMin":90,"faculty":"AwP4.0s1 / EEs1","group":"L1","instructor":"prof. K. Tomczyk / dr inż. M. Sieja","room":"208B","startTime":"12:00","status":"aktywne","subject":"Pomiary elektryczne wielkości nieelektrycznych","type":"laboratoria"},{"date":"2026-06-02","durationMin":90,"faculty":"AwP4.0s1 / EEs1","group":"W","instructor":"dr inż. M. Pawlik","room":"9","startTime":"14:30","status":"aktywne","subject":"Inżynieria sterowania","type":"wykład"},{"date":"2026-06-02","durationMin":90,"faculty":"AwP4.0s1 / EEs1","group":"Lk1","instructor":"dr inż. M. Pawlik","room":"18","startTime":"16:15","status":"aktywne","subject":"Inżynieria sterowania","type":"laboratoria"},{"date":"2026-06-02","durationMin":90,"faculty":"AwP4.0s1 / EEs1","group":"Lk2","instructor":"dr inż. M. Pawlik","room":"18","startTime":"18:00","status":"aktywne","subject":"Inżynieria sterowania","type":"laboratoria"},{"date":"2026-06-02","durationMin":90,"faculty":"AwP4.0s1 / EEs1","group":"P2","instructor":"dr inż. S. Żaba","room":"06","startTime":"19:45","status":"aktywne","subject":"Mikrokontrolery i sterowniki programowalne","type":"laboratoria"},{"date":"2026-06-03","durationMin":90,"faculty":"AwP4.0s1 / EEs1","group":"W / C / S","instructor":"mgr T. Kuta","room":"9","startTime":"10:00","status":"aktywne","subject":"Techniki negocjacyjne","type":"wykład"},{"date":"2026-06-04","durationMin":900,"faculty":"AwP4.0s1 / EEs1","group":"Wszystkie grupy","instructor":"Brak","room":"-","startTime":"07:00","status":"wolne","subject":"Boże Ciało","type":"święto"},{"date":"2026-06-05","durationMin":900,"faculty":"AwP4.0s1 / EEs1","group":"Wszystkie grupy","instructor":"Brak","room":"-","startTime":"07:00","status":"wolne","subject":"Boże Ciało","type":"święto"},{"date":"2026-06-09","durationMin":90,"faculty":"AwP4.0s1 / EEs1","group":"L2","instructor":"dr inż. M. Sieja","room":"208C","startTime":"12:00","status":"aktywne","subject":"Pomiary elektryczne wielkości nieelektrycznych","type":"laboratoria"},{"date":"2026-06-09","durationMin":90,"faculty":"AwP4.0s1 / EEs1","group":"P1","instructor":"dr inż. M. Pawlik","room":"18","startTime":"16:15","status":"aktywne","subject":"Inżynieria sterowania","type":"laboratoria"},{"date":"2026-06-09","durationMin":90,"faculty":"AwP4.0s1 / EEs1","group":"P2","instructor":"dr inż. M. Pawlik","room":"18","startTime":"18:00","status":"aktywne","subject":"Inżynieria sterowania","type":"laboratoria"},{"date":"2026-06-15","durationMin":90,"faculty":"AwP4.0s1 / EEs1","group":"W","instructor":"prof. K. Tomczyk","room":"A1","startTime":"16:15","status":"aktywne","subject":"Pomiary elektryczne wielkości nieelektrycznych","type":"wykład"},{"date":"2026-06-16","durationMin":45,"faculty":"AwP4.0s1 / EEs1","group":"L3","instructor":"prof. K. Tomczyk","room":"208B","startTime":"10:15","status":"aktywne","subject":"Pomiary elektryczne wielkości nieelektrycznych","type":"laboratoria"},{"date":"2026-06-16","durationMin":45,"faculty":"AwP4.0s1 / EEs1","group":"L1","instructor":"prof. K. Tomczyk / dr inż. M. Sieja","room":"208B","startTime":"12:00","status":"aktywne","subject":"Pomiary elektryczne wielkości nieelektrycznych","type":"laboratoria"},{"date":"2026-06-16","durationMin":45,"faculty":"AwP4.0s1 / EEs1","group":"W","instructor":"dr inż. M. Pawlik","room":"9","startTime":"14:30","status":"aktywne","subject":"Inżynieria sterowania","type":"wykład"},{"date":"2026-06-16","durationMin":45,"faculty":"AwP4.0s1 / EEs1","group":"Lk1","instructor":"dr inż. M. Pawlik","room":"18","startTime":"16:15","status":"aktywne","subject":"Inżynieria sterowania","type":"laboratoria"},{"date":"2026-06-16","durationMin":45,"faculty":"AwP4.0s1 / EEs1","group":"Lk2","instructor":"dr inż. M. Pawlik","room":"18","startTime":"18:00","status":"aktywne","subject":"Inżynieria sterowania","type":"laboratoria"},{"date":"2026-06-16","durationMin":45,"faculty":"AwP4.0s1 / EEs1","group":"P2","instructor":"dr inż. S. Żaba","room":"06","startTime":"19:45","status":"aktywne","subject":"Mikrokontrolery i sterowniki programowalne","type":"laboratoria"}]}