{"facultyName":"Its3","events":[{"date":"05-03-2026","durationMin":135,"faculty":"Its3","group":"W","instructor":"prof. R. Sałat","room":"WA2","startTime":"18:00","status":"aktywne","subject":"Systemy SCADA w zarządzaniu procesami przemysłowymi","type":"wykład"},{"date":"19-03-2026","durationMin":135,"faculty":"Its3","group":"W","instructor":"prof. R. Sałat","room":"WA2","startTime":"18:00","status":"aktywne","subject":"Systemy SCADA w zarządzaniu procesami przemysłowymi","type":"wykład"},{"date":"02-04-2026","durationMin":135,"faculty":"Its3","group":"W","instructor":"prof. R. Sałat","room":"WA2","startTime":"18:00","status":"aktywne","subject":"Systemy SCADA w zarządzaniu procesami przemysłowymi","type":"wykład"},{"date":"16-04-2026","durationMin":135,"faculty":"Its3","group":"W","instructor":"prof. R. Sałat","room":"WA2","startTime":"18:00","status":"aktywne","subject":"Systemy SCADA w zarządzaniu procesami przemysłowymi","type":"wykład"},{"date":"30-04-2026","durationMin":135,"faculty":"Its3","group":"W","instructor":"prof. R. Sałat","room":"WA2","startTime":"18:00","status":"aktywne","subject":"Systemy SCADA w zarządzaniu procesami przemysłowymi","type":"wykład"},{"date":"14-05-2026","durationMin":135,"faculty":"Its3","group":"W","instructor":"prof. R. Sałat","room":"WA2","startTime":"18:00","status":"aktywne","subject":"Systemy SCADA w zarządzaniu procesami przemysłowymi","type":"wykład"},{"date":"27-02-2026","durationMin":135,"faculty":"Its3","group":"L1","instructor":"prof. R. Sałat","room":"WA2","startTime":"10:00","status":"aktywne","subject":"Systemy SCADA w zarządzaniu procesami przemysłowymi","type":"laboratoria"},{"date":"06-03-2026","durationMin":135,"faculty":"Its3","group":"L1","instructor":"prof. R. Sałat","room":"WA2","startTime":"10:00","status":"aktywne","subject":"Systemy SCADA w zarządzaniu procesami przemysłowymi","type":"laboratoria"},{"date":"13-03-2026","durationMin":135,"faculty":"Its3","group":"L1","instructor":"prof. R. Sałat","room":"WA2","startTime":"10:00","status":"aktywne","subject":"Systemy SCADA w zarządzaniu procesami przemysłowymi","type":"laboratoria"},{"date":"20-03-2026","durationMin":135,"faculty":"Its3","group":"L1","instructor":"prof. R. Sałat","room":"WA2","startTime":"10:00","status":"aktywne","subject":"Systemy SCADA w zarządzaniu procesami przemysłowymi","type":"laboratoria"},{"date":"27-03-2026","durationMin":135,"faculty":"Its3","group":"L1","instructor":"prof. R. Sałat","room":"WA2","startTime":"10:00","status":"aktywne","subject":"Systemy SCADA w zarządzaniu procesami przemysłowymi","type":"laboratoria"},{"date":"03-04-2026","durationMin":135,"faculty":"Its3","group":"L1","instructor":"prof. R. Sałat","room":"WA2","startTime":"10:00","status":"aktywne","subject":"Systemy SCADA w zarządzaniu procesami przemysłowymi","type":"laboratoria"},{"date":"10-04-2026","durationMin":135,"faculty":"Its3","group":"L1","instructor":"prof. R. Sałat","room":"WA2","startTime":"10:00","status":"aktywne","subject":"Systemy SCADA w zarządzaniu procesami przemysłowymi","type":"laboratoria"},{"date":"17-04-2026","durationMin":135,"faculty":"Its3","group":"L1","instructor":"prof. R. Sałat","room":"WA2","startTime":"10:00","status":"aktywne","subject":"Systemy SCADA w zarządzaniu procesami przemysłowymi","type":"laboratoria"},{"date":"24-04-2026","durationMin":135,"faculty":"Its3","group":"L1","instructor":"prof. R. Sałat","room":"WA2","startTime":"10:00","status":"aktywne","subject":"Systemy SCADA w zarządzaniu procesami przemysłowymi","type":"laboratoria"},{"date":"01-05-2026","durationMin":135,"faculty":"Its3","group":"L1","instructor":"prof. R. Sałat","room":"WA2","startTime":"10:00","status":"aktywne","subject":"Systemy SCADA w zarządzaniu procesami przemysłowymi","type":"laboratoria"},{"date":"08-05-2026","durationMin":135,"faculty":"Its3","group":"L1","instructor":"prof. R. Sałat","room":"WA2","startTime":"10:00","status":"aktywne","subject":"Systemy SCADA w zarządzaniu procesami przemysłowymi","type":"laboratoria"},{"date":"15-05-2026","durationMin":135,"faculty":"Its3","group":"L1","instructor":"prof. R. Sałat","room":"WA2","startTime":"10:00","status":"aktywne","subject":"Systemy SCADA w zarządzaniu procesami przemysłowymi","type":"laboratoria"},{"date":"27-02-2026","durationMin":135,"faculty":"Its3","group":"L2","instructor":"prof. R. Sałat","room":"WA2","startTime":"12:30","status":"aktywne","subject":"Systemy SCADA w zarządzaniu procesami przemysłowymi","type":"laboratoria"},{"date":"06-03-2026","durationMin":135,"faculty":"Its3","group":"L2","instructor":"prof. R. Sałat","room":"WA2","startTime":"12:30","status":"aktywne","subject":"Systemy SCADA w zarządzaniu procesami przemysłowymi","type":"laboratoria"},{"date":"13-03-2026","durationMin":135,"faculty":"Its3","group":"L2","instructor":"prof. R. Sałat","room":"WA2","startTime":"12:30","status":"aktywne","subject":"Systemy SCADA w zarządzaniu procesami przemysłowymi","type":"laboratoria"},{"date":"20-03-2026","durationMin":135,"faculty":"Its3","group":"L2","instructor":"prof. R. Sałat","room":"WA2","startTime":"12:30","status":"aktywne","subject":"Systemy SCADA w zarządzaniu procesami przemysłowymi","type":"laboratoria"},{"date":"27-03-2026","durationMin":135,"faculty":"Its3","group":"L2","instructor":"prof. R. Sałat","room":"WA2","startTime":"12:30","status":"aktywne","subject":"Systemy SCADA w zarządzaniu procesami przemysłowymi","type":"laboratoria"},{"date":"03-04-2026","durationMin":135,"faculty":"Its3","group":"L2","instructor":"prof. R. Sałat","room":"WA2","startTime":"12:30","status":"aktywne","subject":"Systemy SCADA w zarządzaniu procesami przemysłowymi","type":"laboratoria"},{"date":"10-04-2026","durationMin":135,"faculty":"Its3","group":"L2","instructor":"prof. R. Sałat","room":"WA2","startTime":"12:30","status":"aktywne","subject":"Systemy SCADA w zarządzaniu procesami przemysłowymi","type":"laboratoria"},{"date":"17-04-2026","durationMin":135,"faculty":"Its3","group":"L2","instructor":"prof. R. Sałat","room":"WA2","startTime":"12:30","status":"aktywne","subject":"Systemy SCADA w zarządzaniu procesami przemysłowymi","type":"laboratoria"},{"date":"24-04-2026","durationMin":135,"faculty":"Its3","group":"L2","instructor":"prof. R. Sałat","room":"WA2","startTime":"12:30","status":"aktywne","subject":"Systemy SCADA w zarządzaniu procesami przemysłowymi","type":"laboratoria"},{"date":"01-05-2026","durationMin":135,"faculty":"Its3","group":"L2","instructor":"prof. R. Sałat","room":"WA2","startTime":"12:30","status":"aktywne","subject":"Systemy SCADA w zarządzaniu procesami przemysłowymi","type":"laboratoria"},{"date":"08-05-2026","durationMin":135,"faculty":"Its3","group":"L2","instructor":"prof. R. Sałat","room":"WA2","startTime":"12:30","status":"aktywne","subject":"Systemy SCADA w zarządzaniu procesami przemysłowymi","type":"laboratoria"},{"date":"15-05-2026","durationMin":135,"faculty":"Its3","group":"L2","instructor":"prof. R. Sałat","room":"WA2","startTime":"12:30","status":"aktywne","subject":"Systemy SCADA w zarządzaniu procesami przemysłowymi","type":"laboratoria"},{"date":"27-02-2026","durationMin":135,"faculty":"Its3","group":"L3","instructor":"prof. R. Sałat","room":"WA2","startTime":"15:00","status":"aktywne","subject":"Systemy SCADA w zarządzaniu procesami przemysłowymi","type":"laboratoria"},{"date":"06-03-2026","durationMin":135,"faculty":"Its3","group":"L3","instructor":"prof. R. Sałat","room":"WA2","startTime":"15:00","status":"aktywne","subject":"Systemy SCADA w zarządzaniu procesami przemysłowymi","type":"laboratoria"},{"date":"13-03-2026","durationMin":135,"faculty":"Its3","group":"L3","instructor":"prof. R. Sałat","room":"WA2","startTime":"15:00","status":"aktywne","subject":"Systemy SCADA w zarządzaniu procesami przemysłowymi","type":"laboratoria"},{"date":"20-03-2026","durationMin":135,"faculty":"Its3","group":"L3","instructor":"prof. R. Sałat","room":"WA2","startTime":"15:00","status":"aktywne","subject":"Systemy SCADA w zarządzaniu procesami przemysłowymi","type":"laboratoria"},{"date":"27-03-2026","durationMin":135,"faculty":"Its3","group":"L3","instructor":"prof. R. Sałat","room":"WA2","startTime":"15:00","status":"aktywne","subject":"Systemy SCADA w zarządzaniu procesami przemysłowymi","type":"laboratoria"},{"date":"03-04-2026","durationMin":135,"faculty":"Its3","group":"L3","instructor":"prof. R. Sałat","room":"WA2","startTime":"15:00","status":"aktywne","subject":"Systemy SCADA w zarządzaniu procesami przemysłowymi","type":"laboratoria"},{"date":"10-04-2026","durationMin":135,"faculty":"Its3","group":"L3","instructor":"prof. R. Sałat","room":"WA2","startTime":"15:00","status":"aktywne","subject":"Systemy SCADA w zarządzaniu procesami przemysłowymi","type":"laboratoria"},{"date":"17-04-2026","durationMin":135,"faculty":"Its3","group":"L3","instructor":"prof. R. Sałat","room":"WA2","startTime":"15:00","status":"aktywne","subject":"Systemy SCADA w zarządzaniu procesami przemysłowymi","type":"laboratoria"},{"date":"24-04-2026","durationMin":135,"faculty":"Its3","group":"L3","instructor":"prof. R. Sałat","room":"WA2","startTime":"15:00","status":"aktywne","subject":"Systemy SCADA w zarządzaniu procesami przemysłowymi","type":"laboratoria"},{"date":"01-05-2026","durationMin":135,"faculty":"Its3","group":"L3","instructor":"prof. R. Sałat","room":"WA2","startTime":"15:00","status":"aktywne","subject":"Systemy SCADA w zarządzaniu procesami przemysłowymi","type":"laboratoria"},{"date":"08-05-2026","durationMin":135,"faculty":"Its3","group":"L3","instructor":"prof. R. Sałat","room":"WA2","startTime":"15:00","status":"aktywne","subject":"Systemy SCADA w zarządzaniu procesami przemysłowymi","type":"laboratoria"},{"date":"15-05-2026","durationMin":135,"faculty":"Its3","group":"L3","instructor":"prof. R. Sałat","room":"WA2","startTime":"15:00","status":"aktywne","subject":"Systemy SCADA w zarządzaniu procesami przemysłowymi","type":"laboratoria"},{"date":"25-02-2026","durationMin":90,"faculty":"Its3","group":"P1","instructor":"dr inż. A. Romańska","room":"WA201","startTime":"12:45","status":"aktywne","subject":"Systemy informatyczne w zarządzaniu budynkami inteligentnymi","type":"laboratoria"},{"date":"04-03-2026","durationMin":90,"faculty":"Its3","group":"P1","instructor":"dr inż. A. Romańska","room":"WA201","startTime":"12:45","status":"aktywne","subject":"Systemy informatyczne w zarządzaniu budynkami inteligentnymi","type":"laboratoria"},{"date":"11-03-2026","durationMin":90,"faculty":"Its3","group":"P1","instructor":"dr inż. A. Romańska","room":"WA201","startTime":"12:45","status":"aktywne","subject":"Systemy informatyczne w zarządzaniu budynkami inteligentnymi","type":"laboratoria"},{"date":"18-03-2026","durationMin":90,"faculty":"Its3","group":"P1","instructor":"dr inż. A. Romańska","room":"WA201","startTime":"12:45","status":"aktywne","subject":"Systemy informatyczne w zarządzaniu budynkami inteligentnymi","type":"laboratoria"},{"date":"25-03-2026","durationMin":90,"faculty":"Its3","group":"P1","instructor":"dr inż. A. Romańska","room":"WA201","startTime":"12:45","status":"aktywne","subject":"Systemy informatyczne w zarządzaniu budynkami inteligentnymi","type":"laboratoria"},{"date":"01-04-2026","durationMin":90,"faculty":"Its3","group":"P1","instructor":"dr inż. A. Romańska","room":"WA201","startTime":"12:45","status":"aktywne","subject":"Systemy informatyczne w zarządzaniu budynkami inteligentnymi","type":"laboratoria"},{"date":"08-04-2026","durationMin":90,"faculty":"Its3","group":"P1","instructor":"dr inż. A. Romańska","room":"WA201","startTime":"12:45","status":"aktywne","subject":"Systemy informatyczne w zarządzaniu budynkami inteligentnymi","type":"laboratoria"},{"date":"15-04-2026","durationMin":90,"faculty":"Its3","group":"P1","instructor":"dr inż. A. Romańska","room":"WA201","startTime":"12:45","status":"aktywne","subject":"Systemy informatyczne w zarządzaniu budynkami inteligentnymi","type":"laboratoria"},{"date":"22-04-2026","durationMin":90,"faculty":"Its3","group":"P1","instructor":"dr inż. A. Romańska","room":"WA201","startTime":"12:45","status":"aktywne","subject":"Systemy informatyczne w zarządzaniu budynkami inteligentnymi","type":"laboratoria"},{"date":"25-02-2026","durationMin":90,"faculty":"Its3","group":"P2","instructor":"dr inż. A. Romańska","room":"WA201","startTime":"16:15","status":"aktywne","subject":"Systemy informatyczne w zarządzaniu budynkami inteligentnymi","type":"laboratoria"},{"date":"04-03-2026","durationMin":90,"faculty":"Its3","group":"P2","instructor":"dr inż. A. Romańska","room":"WA201","startTime":"16:15","status":"aktywne","subject":"Systemy informatyczne w zarządzaniu budynkami inteligentnymi","type":"laboratoria"},{"date":"11-03-2026","durationMin":90,"faculty":"Its3","group":"P2","instructor":"dr inż. A. Romańska","room":"WA201","startTime":"16:15","status":"aktywne","subject":"Systemy informatyczne w zarządzaniu budynkami inteligentnymi","type":"laboratoria"},{"date":"18-03-2026","durationMin":90,"faculty":"Its3","group":"P2","instructor":"dr inż. A. Romańska","room":"WA201","startTime":"16:15","status":"aktywne","subject":"Systemy informatyczne w zarządzaniu budynkami inteligentnymi","type":"laboratoria"},{"date":"25-03-2026","durationMin":90,"faculty":"Its3","group":"P2","instructor":"dr inż. A. Romańska","room":"WA201","startTime":"16:15","status":"aktywne","subject":"Systemy informatyczne w zarządzaniu budynkami inteligentnymi","type":"laboratoria"},{"date":"01-04-2026","durationMin":90,"faculty":"Its3","group":"P2","instructor":"dr inż. A. Romańska","room":"WA201","startTime":"16:15","status":"aktywne","subject":"Systemy informatyczne w zarządzaniu budynkami inteligentnymi","type":"laboratoria"},{"date":"08-04-2026","durationMin":90,"faculty":"Its3","group":"P2","instructor":"dr inż. A. Romańska","room":"WA201","startTime":"16:15","status":"aktywne","subject":"Systemy informatyczne w zarządzaniu budynkami inteligentnymi","type":"laboratoria"},{"date":"15-04-2026","durationMin":90,"faculty":"Its3","group":"P2","instructor":"dr inż. A. Romańska","room":"WA201","startTime":"16:15","status":"aktywne","subject":"Systemy informatyczne w zarządzaniu budynkami inteligentnymi","type":"laboratoria"},{"date":"22-04-2026","durationMin":90,"faculty":"Its3","group":"P2","instructor":"dr inż. A. Romańska","room":"WA201","startTime":"16:15","status":"aktywne","subject":"Systemy informatyczne w zarządzaniu budynkami inteligentnymi","type":"laboratoria"},{"date":"26-02-2026","durationMin":90,"faculty":"Its3","group":"W","instructor":"dr inż. A. Romańska","room":"9","startTime":"16:15","status":"aktywne","subject":"Systemy informatyczne w zarządzaniu budynkami inteligentnymi","type":"wykład"},{"date":"05-03-2026","durationMin":90,"faculty":"Its3","group":"W","instructor":"dr inż. A. Romańska","room":"9","startTime":"16:15","status":"aktywne","subject":"Systemy informatyczne w zarządzaniu budynkami inteligentnymi","type":"wykład"},{"date":"12-03-2026","durationMin":90,"faculty":"Its3","group":"W","instructor":"dr inż. A. Romańska","room":"9","startTime":"16:15","status":"aktywne","subject":"Systemy informatyczne w zarządzaniu budynkami inteligentnymi","type":"wykład"},{"date":"19-03-2026","durationMin":90,"faculty":"Its3","group":"W","instructor":"dr inż. A. Romańska","room":"9","startTime":"16:15","status":"aktywne","subject":"Systemy informatyczne w zarządzaniu budynkami inteligentnymi","type":"wykład"},{"date":"26-03-2026","durationMin":90,"faculty":"Its3","group":"W","instructor":"dr inż. A. Romańska","room":"9","startTime":"16:15","status":"aktywne","subject":"Systemy informatyczne w zarządzaniu budynkami inteligentnymi","type":"wykład"},{"date":"02-04-2026","durationMin":90,"faculty":"Its3","group":"W","instructor":"dr inż. A. Romańska","room":"9","startTime":"16:15","status":"aktywne","subject":"Systemy informatyczne w zarządzaniu budynkami inteligentnymi","type":"wykład"},{"date":"09-04-2026","durationMin":90,"faculty":"Its3","group":"W","instructor":"dr inż. A. Romańska","room":"9","startTime":"16:15","status":"aktywne","subject":"Systemy informatyczne w zarządzaniu budynkami inteligentnymi","type":"wykład"},{"date":"16-04-2026","durationMin":90,"faculty":"Its3","group":"W","instructor":"dr inż. A. Romańska","room":"9","startTime":"16:15","status":"aktywne","subject":"Systemy informatyczne w zarządzaniu budynkami inteligentnymi","type":"wykład"},{"date":"23-04-2026","durationMin":90,"faculty":"Its3","group":"W","instructor":"dr inż. A. Romańska","room":"9","startTime":"16:15","status":"aktywne","subject":"Systemy informatyczne w zarządzaniu budynkami inteligentnymi","type":"wykład"},{"date":"24-02-2026","durationMin":90,"faculty":"Its3","group":"P1","instructor":"mgr inż. K. Sołtys","room":"12","startTime":"12:45","status":"aktywne","subject":"Nowoczesne magazyny energii","type":"laboratoria"},{"date":"03-03-2026","durationMin":90,"faculty":"Its3","group":"P1","instructor":"mgr inż. K. Sołtys","room":"12","startTime":"12:45","status":"aktywne","subject":"Nowoczesne magazyny energii","type":"laboratoria"},{"date":"10-03-2026","durationMin":90,"faculty":"Its3","group":"P1","instructor":"mgr inż. K. Sołtys","room":"12","startTime":"12:45","status":"aktywne","subject":"Nowoczesne magazyny energii","type":"laboratoria"},{"date":"17-03-2026","durationMin":90,"faculty":"Its3","group":"P1","instructor":"mgr inż. K. Sołtys","room":"12","startTime":"12:45","status":"aktywne","subject":"Nowoczesne magazyny energii","type":"laboratoria"},{"date":"24-03-2026","durationMin":90,"faculty":"Its3","group":"P1","instructor":"mgr inż. K. Sołtys","room":"12","startTime":"12:45","status":"aktywne","subject":"Nowoczesne magazyny energii","type":"laboratoria"},{"date":"24-02-2026","durationMin":90,"faculty":"Its3","group":"P2","instructor":"mgr inż. K. Sołtys","room":"12","startTime":"11:00","status":"aktywne","subject":"Nowoczesne magazyny energii","type":"laboratoria"},{"date":"03-03-2026","durationMin":90,"faculty":"Its3","group":"P2","instructor":"mgr inż. K. Sołtys","room":"12","startTime":"11:00","status":"aktywne","subject":"Nowoczesne magazyny energii","type":"laboratoria"},{"date":"10-03-2026","durationMin":90,"faculty":"Its3","group":"P2","instructor":"mgr inż. K. Sołtys","room":"12","startTime":"11:00","status":"aktywne","subject":"Nowoczesne magazyny energii","type":"laboratoria"},{"date":"17-03-2026","durationMin":90,"faculty":"Its3","group":"P2","instructor":"mgr inż. K. Sołtys","room":"12","startTime":"11:00","status":"aktywne","subject":"Nowoczesne magazyny energii","type":"laboratoria"},{"date":"24-03-2026","durationMin":90,"faculty":"Its3","group":"P2","instructor":"mgr inż. K. Sołtys","room":"12","startTime":"11:00","status":"aktywne","subject":"Nowoczesne magazyny energii","type":"laboratoria"},{"date":"24-02-2026","durationMin":90,"faculty":"Its3","group":"Lk2","instructor":"mgr inż. P. Tofilski","room":"13","startTime":"12:45","status":"aktywne","subject":"Nowoczesne magazyny energii","type":"laboratoria"},{"date":"03-03-2026","durationMin":90,"faculty":"Its3","group":"Lk2","instructor":"mgr inż. P. Tofilski","room":"13","startTime":"12:45","status":"aktywne","subject":"Nowoczesne magazyny energii","type":"laboratoria"},{"date":"10-03-2026","durationMin":90,"faculty":"Its3","group":"Lk2","instructor":"mgr inż. P. Tofilski","room":"13","startTime":"12:45","status":"aktywne","subject":"Nowoczesne magazyny energii","type":"laboratoria"},{"date":"17-03-2026","durationMin":90,"faculty":"Its3","group":"Lk2","instructor":"mgr inż. P. Tofilski","room":"13","startTime":"12:45","status":"aktywne","subject":"Nowoczesne magazyny energii","type":"laboratoria"},{"date":"24-03-2026","durationMin":90,"faculty":"Its3","group":"Lk2","instructor":"mgr inż. P. Tofilski","room":"13","startTime":"12:45","status":"aktywne","subject":"Nowoczesne magazyny energii","type":"laboratoria"},{"date":"31-03-2026","durationMin":90,"faculty":"Its3","group":"Lk2","instructor":"mgr inż. P. Tofilski","room":"13","startTime":"12:45","status":"aktywne","subject":"Nowoczesne magazyny energii","type":"laboratoria"},{"date":"07-04-2026","durationMin":90,"faculty":"Its3","group":"Lk2","instructor":"mgr inż. P. Tofilski","room":"13","startTime":"12:45","status":"aktywne","subject":"Nowoczesne magazyny energii","type":"laboratoria"},{"date":"14-04-2026","durationMin":90,"faculty":"Its3","group":"Lk2","instructor":"mgr inż. P. Tofilski","room":"13","startTime":"12:45","status":"aktywne","subject":"Nowoczesne magazyny energii","type":"laboratoria"},{"date":"21-04-2026","durationMin":90,"faculty":"Its3","group":"Lk2","instructor":"mgr inż. P. Tofilski","room":"13","startTime":"12:45","status":"aktywne","subject":"Nowoczesne magazyny energii","type":"laboratoria"},{"date":"24-02-2026","durationMin":90,"faculty":"Its3","group":"Lk1","instructor":"mgr inż. P. Tofilski","room":"13","startTime":"11:00","status":"aktywne","subject":"Nowoczesne magazyny energii","type":"laboratoria"},{"date":"03-03-2026","durationMin":90,"faculty":"Its3","group":"Lk1","instructor":"mgr inż. P. Tofilski","room":"13","startTime":"11:00","status":"aktywne","subject":"Nowoczesne magazyny energii","type":"laboratoria"},{"date":"10-03-2026","durationMin":90,"faculty":"Its3","group":"Lk1","instructor":"mgr inż. P. Tofilski","room":"13","startTime":"11:00","status":"aktywne","subject":"Nowoczesne magazyny energii","type":"laboratoria"},{"date":"17-03-2026","durationMin":90,"faculty":"Its3","group":"Lk1","instructor":"mgr inż. P. Tofilski","room":"13","startTime":"11:00","status":"aktywne","subject":"Nowoczesne magazyny energii","type":"laboratoria"},{"date":"24-03-2026","durationMin":90,"faculty":"Its3","group":"Lk1","instructor":"mgr inż. P. Tofilski","room":"13","startTime":"11:00","status":"aktywne","subject":"Nowoczesne magazyny energii","type":"laboratoria"},{"date":"31-03-2026","durationMin":90,"faculty":"Its3","group":"Lk1","instructor":"mgr inż. P. Tofilski","room":"13","startTime":"11:00","status":"aktywne","subject":"Nowoczesne magazyny energii","type":"laboratoria"},{"date":"07-04-2026","durationMin":90,"faculty":"Its3","group":"Lk1","instructor":"mgr inż. P. Tofilski","room":"13","startTime":"11:00","status":"aktywne","subject":"Nowoczesne magazyny energii","type":"laboratoria"},{"date":"14-04-2026","durationMin":90,"faculty":"Its3","group":"Lk1","instructor":"mgr inż. P. Tofilski","room":"13","startTime":"11:00","status":"aktywne","subject":"Nowoczesne magazyny energii","type":"laboratoria"},{"date":"21-04-2026","durationMin":90,"faculty":"Its3","group":"Lk1","instructor":"mgr inż. P. Tofilski","room":"13","startTime":"11:00","status":"aktywne","subject":"Nowoczesne magazyny energii","type":"laboratoria"},{"date":"26-02-2026","durationMin":180,"faculty":"Its3","group":"W","instructor":"dr inż. S. Bartel","room":"9","startTime":"09:15","status":"aktywne","subject":"Nowoczesne magazyny energii","type":"wykład"},{"date":"05-03-2026","durationMin":180,"faculty":"Its3","group":"W","instructor":"dr inż. S. Bartel","room":"9","startTime":"09:15","status":"aktywne","subject":"Nowoczesne magazyny energii","type":"wykład"},{"date":"12-03-2026","durationMin":180,"faculty":"Its3","group":"W","instructor":"dr inż. S. Bartel","room":"9","startTime":"09:15","status":"aktywne","subject":"Nowoczesne magazyny energii","type":"wykład"},{"date":"19-03-2026","durationMin":135,"faculty":"Its3","group":"W","instructor":"dr inż. S. Bartel","room":"9","startTime":"10:00","status":"aktywne","subject":"Nowoczesne magazyny energii","type":"wykład"},{"date":"24-02-2026","durationMin":135,"faculty":"Its3","group":"S1","instructor":"prof. K. Kluszczyński","room":"10","startTime":"14:30","status":"aktywne","subject":"Seminarium dyplomowe","type":"laboratoria"},{"date":"03-03-2026","durationMin":135,"faculty":"Its3","group":"S1","instructor":"prof. K. Kluszczyński","room":"10","startTime":"14:30","status":"aktywne","subject":"Seminarium dyplomowe","type":"laboratoria"},{"date":"10-03-2026","durationMin":135,"faculty":"Its3","group":"S1","instructor":"prof. K. Kluszczyński","room":"10","startTime":"16:15","status":"aktywne","subject":"Seminarium dyplomowe","type":"laboratoria"},{"date":"24-03-2026","durationMin":135,"faculty":"Its3","group":"S1","instructor":"prof. K. Kluszczyński","room":"10","startTime":"16:15","status":"aktywne","subject":"Seminarium dyplomowe","type":"laboratoria"},{"date":"31-03-2026","durationMin":135,"faculty":"Its3","group":"S1","instructor":"prof. K. Kluszczyński","room":"10","startTime":"16:15","status":"aktywne","subject":"Seminarium dyplomowe","type":"laboratoria"},{"date":"07-04-2026","durationMin":135,"faculty":"Its3","group":"S1","instructor":"prof. K. Kluszczyński","room":"10","startTime":"16:15","status":"aktywne","subject":"Seminarium dyplomowe","type":"laboratoria"},{"date":"14-04-2026","durationMin":135,"faculty":"Its3","group":"S1","instructor":"prof. K. Kluszczyński","room":"10","startTime":"16:15","status":"aktywne","subject":"Seminarium dyplomowe","type":"laboratoria"},{"date":"21-04-2026","durationMin":135,"faculty":"Its3","group":"S1","instructor":"prof. K. Kluszczyński","room":"10","startTime":"16:15","status":"aktywne","subject":"Seminarium dyplomowe","type":"laboratoria"},{"date":"28-04-2026","durationMin":135,"faculty":"Its3","group":"S1","instructor":"prof. K. Kluszczyński","room":"10","startTime":"14:30","status":"aktywne","subject":"Seminarium dyplomowe","type":"laboratoria"},{"date":"05-05-2026","durationMin":135,"faculty":"Its3","group":"S1","instructor":"prof. K. Kluszczyński","room":"10","startTime":"14:30","status":"aktywne","subject":"Seminarium dyplomowe","type":"laboratoria"},{"date":"12-05-2026","durationMin":135,"faculty":"Its3","group":"S1","instructor":"prof. K. Kluszczyński","room":"10","startTime":"16:15","status":"aktywne","subject":"Seminarium dyplomowe","type":"laboratoria"},{"date":"26-05-2026","durationMin":135,"faculty":"Its3","group":"S1","instructor":"prof. K. Kluszczyński","room":"10","startTime":"16:00","status":"aktywne","subject":"Seminarium dyplomowe","type":"laboratoria"},{"date":"10-03-2026","durationMin":90,"faculty":"Its3","group":"S1","instructor":"prof. K. Kluszczyński","room":"10","startTime":"14:30","status":"aktywne","subject":"Sztuka redagowania, dyskusji i prezentacji","type":"laboratoria"},{"date":"24-03-2026","durationMin":90,"faculty":"Its3","group":"S1","instructor":"prof. K. Kluszczyński","room":"10","startTime":"14:30","status":"aktywne","subject":"Sztuka redagowania, dyskusji i prezentacji","type":"laboratoria"},{"date":"31-03-2026","durationMin":90,"faculty":"Its3","group":"S1","instructor":"prof. K. Kluszczyński","room":"10","startTime":"14:30","status":"aktywne","subject":"Sztuka redagowania, dyskusji i prezentacji","type":"laboratoria"},{"date":"07-04-2026","durationMin":90,"faculty":"Its3","group":"S1","instructor":"prof. K. Kluszczyński","room":"10","startTime":"14:30","status":"aktywne","subject":"Sztuka redagowania, dyskusji i prezentacji","type":"laboratoria"},{"date":"14-04-2026","durationMin":90,"faculty":"Its3","group":"S1","instructor":"prof. K. Kluszczyński","room":"10","startTime":"14:30","status":"aktywne","subject":"Sztuka redagowania, dyskusji i prezentacji","type":"laboratoria"},{"date":"21-04-2026","durationMin":90,"faculty":"Its3","group":"S1","instructor":"prof. K. Kluszczyński","room":"10","startTime":"14:30","status":"aktywne","subject":"Sztuka redagowania, dyskusji i prezentacji","type":"laboratoria"}]}